clickmod_auth/__init__.py
clickmod_auth/auth.py
clickmod_auth/errors.py
clickmod_auth/middleware.py
clickmod_auth/plugin.py
clickmod_auth/utils.py
clickmod_auth-0.1.1.dist-info/METADATA
clickmod_auth-0.1.1.dist-info/WHEEL
clickmod_auth-0.1.1.dist-info/entry_points.txt
clickmod_auth-0.1.1.dist-info/RECORD
