Metadata-Version: 2.1
Name: clickmod-auth
Version: 0.1.1
Summary: ClickMod authentication module.
License: MIT
Author: Luke Hodkinson
Author-email: furious.luke@gmail.com
Requires-Python: >=3.7,<3.11
Classifier: License :: OSI Approved :: MIT License
Classifier: Programming Language :: Python :: 3
Classifier: Programming Language :: Python :: 3.7
Classifier: Programming Language :: Python :: 3.8
Classifier: Programming Language :: Python :: 3.9
Classifier: Programming Language :: Python :: 3.10
Requires-Dist: click (>=8.0.1,<9.0.0)
Requires-Dist: python-gnupg (>=0.5.0,<0.6.0)
Requires-Dist: rich (>=12.5.1,<13.0.0)
